{
  "prepare_queue": {
    "installed": [],
    "uninstalled": []
  },
  "config_munge": {
    "files": {}
  },
  "installed_plugins": {
    "cordova-plugin-whitelist": {
      "PACKAGE_NAME": "com.phonegap.ecommercesimple"
    },
    "cordova-plugin-crosswalk-webview": {
      "PACKAGE_NAME": "com.phonegap.ecommercesimple"
    },
    "cordova-plugin-camera": {
      "PACKAGE_NAME": "com.phonegap.ecommercesimple"
    },
    "cordova-plugin-media-capture": {
      "PACKAGE_NAME": "com.phonegap.ecommercesimple"
    },
    "cordova-plugin-device": {
      "PACKAGE_NAME": "com.phonegap.ecommercesimple"
    },
    "cordova-plugin-file": {
      "PACKAGE_NAME": "com.phonegap.ecommercesimple"
    },
    "cordova-plugin-media": {
      "PACKAGE_NAME": "com.phonegap.ecommercesimple"
    },
    "cordova-plugin-contacts": {
      "PACKAGE_NAME": "com.phonegap.ecommercesimple"
    },
    "cordova-plugin-android-permissions": {
      "PACKAGE_NAME": "com.phonegap.ecommercesimple"
    }
  },
  "dependent_plugins": {}
}